errui/__init__.py
errui/abort.py
errui/base.py
errui/report.py
errui-0.1.0.dist-info/WHEEL
errui-0.1.0.dist-info/METADATA
errui-0.1.0.dist-info/RECORD
