Metadata-Version: 2.1
Name: errui
Version: 0.1.0
Summary: Error handling for end users
Home-page: https://gitlab.com/deepadmax/errui
Author: Maximillian Strand
Author-email: maximillian.strand@protonmail.com
Requires-Python: >=3.9,<4.0
Classifier: Programming Language :: Python :: 3
Classifier: Programming Language :: Python :: 3.10
Classifier: Programming Language :: Python :: 3.9
Project-URL: Repository, https://gitlab.com/deepadmax/errui
